pcof/__init__.py
pcof/__version__.py
pcof/bytesconv.py
pcof/datetimefunc.py
pcof/decorators.py
pcof/downloadfile.py
pcof/misc.py
pcof/pct.py
pcof/printtable.py
pcof/pytz.py
pcof-0.2.1.dist-info/LICENSE
pcof-0.2.1.dist-info/METADATA
pcof-0.2.1.dist-info/WHEEL
pcof-0.2.1.dist-info/top_level.txt
pcof-0.2.1.dist-info/RECORD
