Metadata-Version: 2.1
Name: pcof
Version: 0.2.1
Summary: Python Collection Of Functions.
Home-page: https://github.com/thobiast/pcof
Author: Thobias Salazar Trevisan
License: MIT
Platform: UNKNOWN
Classifier: License :: OSI Approved :: MIT License
Classifier: Environment :: Console
Classifier: Topic :: Software Development
Classifier: Topic :: Terminals
Classifier: Topic :: Utilities
Classifier: Programming Language :: Python :: 3
Classifier: Intended Audience :: Developers
Classifier: Intended Audience :: System Administrators
Classifier: Operating System :: OS Independent
Classifier: Topic :: Software Development :: Libraries :: Python Modules
Requires-Dist: prettytable
Requires-Dist: pytz
Requires-Dist: requests
